Metadata-Version: 1.0
Name: home-electric-usage-recommendation-modules
Version: 0.0.3
Summary: modules for household's electric usage recommendation
Home-page: UNKNOWN
Author: Shintaro Ikeda
Author-email: ikenshirogivenup98@gmail.com
License: MIT
Platform: UNKNOWN
